{
  "vendors.js": "/zet-ui/static/js/vendors.2e111146.js",
  "vendors.js.map": "/zet-ui/static/js/vendors.322882f5e10f6d89b4dc.js.map",
  "app.js": "/zet-ui/static/js/app.e1df41d3.js",
  "app.js.map": "/zet-ui/static/js/app.322882f5e10f6d89b4dc.js.map",
  "runtime~app.js": "/zet-ui/static/js/runtime~app.322882f5e10f6d89b4dc.js",
  "runtime~app.js.map": "/zet-ui/static/js/runtime~app.322882f5e10f6d89b4dc.js.map",
  "src-components-resource-index.css": "/zet-ui/static/css/src-components-resource-index.322882f5e10f6d89b4dc.css",
  "src-components-resource-index.js": "/zet-ui/static/js/src-components-resource-index.9adae3b0.js",
  "src-components-resource-index.js.map": "/zet-ui/static/js/src-components-resource-index.322882f5e10f6d89b4dc.js.map",
  "src-components-tag-index.js": "/zet-ui/static/js/src-components-tag-index.563cf77e.js",
  "src-components-tag-index.js.map": "/zet-ui/static/js/src-components-tag-index.322882f5e10f6d89b4dc.js.map",
  "src-index.js": "/zet-ui/static/js/src-index.28e7f090.js",
  "src-index.js.map": "/zet-ui/static/js/src-index.322882f5e10f6d89b4dc.js.map",
  "static/js/6.e358a374.js": "/zet-ui/static/js/6.e358a374.js",
  "static/js/6.322882f5e10f6d89b4dc.js.map": "/zet-ui/static/js/6.322882f5e10f6d89b4dc.js.map",
  "index.html": "/zet-ui/index.html"
}